inngest_encryption/__init__.py
inngest_encryption/main.py
inngest_encryption/py.typed
inngest_encryption-0.1.0.dist-info/METADATA
inngest_encryption-0.1.0.dist-info/WHEEL
inngest_encryption-0.1.0.dist-info/top_level.txt
inngest_encryption-0.1.0.dist-info/RECORD
