Metadata-Version: 2.2
Name: inngest_encryption
Version: 0.1.0
Summary: Encryption for the Inngest SDK
Author-email: "Inngest Inc." <hello@inngest.com>
Project-URL: Homepage, https://github.com/inngest/inngest-py
Project-URL: Bug Tracker, https://github.com/inngest/inngest-py/issues
Classifier: Development Status :: 3 - Alpha
Classifier: Intended Audience :: Developers
Classifier: Programming Language :: Python :: 3.9
Classifier: Programming Language :: Python :: 3.10
Classifier: Programming Language :: Python :: 3.11
Classifier: Programming Language :: Python :: 3.12
Requires-Python: >=3.9
Requires-Dist: inngest>=0.4.18
Requires-Dist: pynacl>=1.5.0
